{
  "toilet": [
    {
      "Field": "toilet_id",
      "Type": "int",
      "Null": "NO",
      "Key": "PRI",
      "Default": null,
      "Extra": ""
    },
    {
      "Field": "location",
      "Type": "varchar(100)",
      "Null": "YES",
      "Key": "",
      "Default": null,
      "Extra": ""
    },
    {
      "Field": "status",
      "Type": "varchar(20)",
      "Null": "YES",
      "Key": "",
      "Default": null,
      "Extra": ""
    },
    {
      "Field": "last_cleaned_time",
      "Type": "datetime",
      "Null": "YES",
      "Key": "",
      "Default": null,
      "Extra": ""
    }
  ],
  "sensor_data": [
    {
      "Field": "id",
      "Type": "int",
      "Null": "NO",
      "Key": "PRI",
      "Default": null,
      "Extra": "auto_increment"
    },
    {
      "Field": "toilet_id",
      "Type": "int",
      "Null": "NO",
      "Key": "MUL",
      "Default": null,
      "Extra": ""
    },
    {
      "Field": "gas_value",
      "Type": "int",
      "Null": "YES",
      "Key": "",
      "Default": null,
      "Extra": ""
    },
    {
      "Field": "gas_status",
      "Type": "varchar(20)",
      "Null": "YES",
      "Key": "",
      "Default": null,
      "Extra": ""
    },
    {
      "Field": "odour_level",
      "Type": "float",
      "Null": "YES",
      "Key": "",
      "Default": null,
      "Extra": ""
    },
    {
      "Field": "distance",
      "Type": "float",
      "Null": "YES",
      "Key": "",
      "Default": null,
      "Extra": ""
    },
    {
      "Field": "status",
      "Type": "varchar(20)",
      "Null": "YES",
      "Key": "",
      "Default": null,
      "Extra": ""
    },
    {
      "Field": "usage_count",
      "Type": "int",
      "Null": "YES",
      "Key": "",
      "Default": null,
      "Extra": ""
    },
    {
      "Field": "alert",
      "Type": "varchar(10)",
      "Null": "YES",
      "Key": "",
      "Default": null,
      "Extra": ""
    },
    {
      "Field": "timestamp",
      "Type": "datetime",
      "Null": "YES",
      "Key": "",
      "Default": "CURRENT_TIMESTAMP",
      "Extra": "DEFAULT_GENERATED"
    }
  ]
}